cm2diffop/Calc_3d.py
cm2diffop/Calc_diff_ops.py
cm2diffop/Get_Diff_Op_mat_vec.py
cm2diffop/Taylor.py
cm2diffop/__init__.py
cm2diffop-0.0.7.dist-info/METADATA
cm2diffop-0.0.7.dist-info/WHEEL
cm2diffop-0.0.7.dist-info/top_level.txt
cm2diffop-0.0.7.dist-info/RECORD
