Metadata-Version: 2.1
Name: cm2diffop
Version: 0.0.7
Summary: differential operator
Home-page: https://gitlab.com/cm2lab/diffop_module
Author: CM2Lab
Author-email: s.park@openest.eu
License: UNKNOWN
Keywords: differential operator
Platform: UNKNOWN
Classifier: Programming Language :: Python :: 3
Classifier: License :: OSI Approved :: MIT License
Classifier: Operating System :: OS Independent
Requires-Python: >=3.6
